jax_dataclasses/__init__.py
jax_dataclasses/_copy_and_mutate.py
jax_dataclasses/_dataclasses.py
jax_dataclasses/_enforced_annotations.py
jax_dataclasses/_get_type_hints.py
jax_dataclasses/_jit.py
jax_dataclasses/py.typed
jax_dataclasses-1.6.3.dist-info/licenses/LICENSE
jax_dataclasses-1.6.3.dist-info/METADATA
jax_dataclasses-1.6.3.dist-info/WHEEL
jax_dataclasses-1.6.3.dist-info/top_level.txt
jax_dataclasses-1.6.3.dist-info/RECORD
