Metadata-Version: 2.4
Name: jax_dataclasses
Version: 1.6.3
Summary: Dataclasses + JAX
Home-page: http://github.com/brentyi/jax_dataclasses
Author: brentyi
Author-email: brentyi@berkeley.edu
License: MIT
Classifier: Programming Language :: Python :: 3.9
Classifier: Programming Language :: Python :: 3.10
Classifier: Programming Language :: Python :: 3.11
Classifier: Programming Language :: Python :: 3.12
Classifier: License :: OSI Approved :: MIT License
Classifier: Operating System :: OS Independent
Requires-Python: >=3.9
License-File: LICENSE
Requires-Dist: jax>=0.4.25
Requires-Dist: jaxlib
Requires-Dist: typing_extensions
Provides-Extra: testing
Requires-Dist: flax; extra == "testing"
Requires-Dist: pytest; extra == "testing"
Requires-Dist: pytest-cov; extra == "testing"
Dynamic: author
Dynamic: author-email
Dynamic: classifier
Dynamic: description
Dynamic: description-content-type
Dynamic: home-page
Dynamic: license
Dynamic: license-file
Dynamic: provides-extra
Dynamic: requires-dist
Dynamic: requires-python
Dynamic: summary
